spacesay/__init__.py
spacesay/location.py
spacesay/main.py
spacesay/speech.py
spacesay-0.1.1.dist-info/LICENSE.md
spacesay-0.1.1.dist-info/METADATA
spacesay-0.1.1.dist-info/WHEEL
spacesay-0.1.1.dist-info/entry_points.txt
spacesay-0.1.1.dist-info/RECORD
