Metadata-Version: 2.1
Name: spacesay
Version: 0.1.1
Summary: A CLI spaceman tells you where the ISS is!
Author: AlgorithmEnigma
Author-email: me@jordanlowell.com
Requires-Python: >=3.10,<4.0
Classifier: Programming Language :: Python :: 3
Classifier: Programming Language :: Python :: 3.10
Classifier: Programming Language :: Python :: 3.11
Requires-Dist: pyyaml (>=6.0,<7.0)
Requires-Dist: requests (>=2.28.2,<3.0.0)
Requires-Dist: typer[all] (>=0.7.0,<0.8.0)
